rai_core_flask/__init__.py
rai_core_flask/environment_detector.py
rai_core_flask/flask_helper.py
rai_core_flask/environments/__init__.py
rai_core_flask/environments/azure_nb_environment.py
rai_core_flask/environments/base_environment.py
rai_core_flask/environments/credentialed_vm_environment.py
rai_core_flask/environments/databricks_environment.py
rai_core_flask/environments/local_ipython_environment.py
rai_core_flask/environments/public_vm_environment.py
rai_core_flask-0.7.6.dist-info/LICENSE
rai_core_flask-0.7.6.dist-info/METADATA
rai_core_flask-0.7.6.dist-info/WHEEL
rai_core_flask-0.7.6.dist-info/top_level.txt
rai_core_flask-0.7.6.dist-info/RECORD
